pybrctl/__init__.py
pybrctl/pybrctl.py
nbycomp_pybrctl-0.1.4.6.dist-info/LICENSE
nbycomp_pybrctl-0.1.4.6.dist-info/METADATA
nbycomp_pybrctl-0.1.4.6.dist-info/WHEEL
nbycomp_pybrctl-0.1.4.6.dist-info/top_level.txt
nbycomp_pybrctl-0.1.4.6.dist-info/RECORD
