Metadata-Version: 2.1
Name: nbycomp-pybrctl
Version: 0.1.4.6
Summary: Python brctl wrapper
Home-page: https://github.com/nbycomp/pybrctl
Author: Ido Nahshon, Oriol Marí
Author-email: udragon@gmail.com, omari@nearbycomputing.com
License: GPLv2
Keywords: brctl,bridge-utils
Platform: UNKNOWN
Classifier: License :: OSI Approved :: GNU General Public License v2 (GPLv2)
Classifier: Programming Language :: Python
Classifier: Operating System :: POSIX
Classifier: Programming Language :: Python :: 2.7
Classifier: Programming Language :: Python :: 3
